{
    "AX": {
        "error": 0.004961724135472302, 
        "filter_outliers_dict": {
            "filter_outliers": true, 
            "iterations": 1, 
            "std_devs": 2
        }, 
        "fit": "average", 
        "value": 0.035656985399913806
    }, 
    "CDD": {
        "error": 1.5683421060594633e-05, 
        "filter_outliers_dict": {
            "filter_outliers": true, 
            "iterations": 1, 
            "std_devs": 10
        }, 
        "fit": "average", 
        "value": 0.00016217922531904568
    }, 
    "H1": {
        "error": 0.0034419535731281307, 
        "filter_outliers_dict": {
            "filter_outliers": true, 
            "iterations": 1, 
            "std_devs": 2
        }, 
        "fit": "average", 
        "value": -0.016935532316643596
    }, 
    "H2": {
        "error": 0.004584834980169349, 
        "filter_outliers_dict": {
            "filter_outliers": true, 
            "iterations": 1, 
            "std_devs": 2
        }, 
        "fit": "average", 
        "value": 0.06266578404722395
    }, 
    "L1": {
        "error": 0.001734727317045856, 
        "filter_outliers_dict": {
            "filter_outliers": true, 
            "iterations": 1, 
            "std_devs": 2
        }, 
        "fit": "average", 
        "value": 0.012107576149494101
    }, 
    "L2": {
        "error": 0.005061680760573795, 
        "filter_outliers_dict": {
            "filter_outliers": true, 
            "iterations": 1, 
            "std_devs": 2
        }, 
        "fit": "average", 
        "value": 0.1333988088067247
    }
}