{
    "AX": {
        "error": 0.004613315783364915, 
        "filter_outliers_dict": {
            "filter_outliers": true, 
            "iterations": 1, 
            "std_devs": 2
        }, 
        "fit": "average", 
        "value": 0.06146925757165425
    }, 
    "CDD": {
        "error": 7.55713010918286e-06, 
        "filter_outliers_dict": {
            "filter_outliers": true, 
            "iterations": 1, 
            "std_devs": 10
        }, 
        "fit": "average", 
        "value": 3.736926695787844e-05
    }, 
    "H1": {
        "error": 0.003383760678361659, 
        "filter_outliers_dict": {
            "filter_outliers": true, 
            "iterations": 1, 
            "std_devs": 2
        }, 
        "fit": "average", 
        "value": 0.17377897086085142
    }, 
    "H2": {
        "error": 0.004618925108885994, 
        "filter_outliers_dict": {
            "filter_outliers": true, 
            "iterations": 1, 
            "std_devs": 2
        }, 
        "fit": "average", 
        "value": 0.09185262177727592
    }, 
    "L1": {
        "error": 0.0017312613558476966, 
        "filter_outliers_dict": {
            "filter_outliers": true, 
            "iterations": 1, 
            "std_devs": 2
        }, 
        "fit": "average", 
        "value": -0.17699392128654737
    }, 
    "L2": {
        "error": 0.00470400926825254, 
        "filter_outliers_dict": {
            "filter_outliers": true, 
            "iterations": 1, 
            "std_devs": 2
        }, 
        "fit": "average", 
        "value": -0.018267118567667485
    }
}