{
    "AX": {
        "error": 0.006158371288441035, 
        "filter_outliers_dict": {
            "filter_outliers": true, 
            "iterations": 1, 
            "std_devs": 2
        }, 
        "fit": "average", 
        "value": -0.009698871774364352
    }, 
    "CDD": {
        "error": 1.7187517210385878e-05, 
        "filter_outliers_dict": {
            "filter_outliers": true, 
            "iterations": 1, 
            "std_devs": 10
        }, 
        "fit": "average", 
        "value": 0.00017036530751848243
    }, 
    "H1": {
        "error": 0.005648712963039941, 
        "filter_outliers_dict": {
            "filter_outliers": true, 
            "iterations": 1, 
            "std_devs": 2
        }, 
        "fit": "average", 
        "value": 0.0012711076242597256
    }, 
    "H2": {
        "error": 0.00608665912800237, 
        "filter_outliers_dict": {
            "filter_outliers": true, 
            "iterations": 1, 
            "std_devs": 2
        }, 
        "fit": "average", 
        "value": -0.14638866574343212
    }, 
    "L1": {
        "error": 0.002935713977751812, 
        "filter_outliers_dict": {
            "filter_outliers": true, 
            "iterations": 1, 
            "std_devs": 2
        }, 
        "fit": "average", 
        "value": -0.021540577130454902
    }, 
    "L2": {
        "error": 0.004941361119383679, 
        "filter_outliers_dict": {
            "filter_outliers": true, 
            "iterations": 1, 
            "std_devs": 2
        }, 
        "fit": "average", 
        "value": -0.021768643815441663
    }
}