{
    "AX": {
        "error": 0.004777625530141326, 
        "filter_outliers_dict": {
            "filter_outliers": true, 
            "iterations": 1, 
            "std_devs": 2
        }, 
        "fit": "average", 
        "value": 0.024569767945005202
    }, 
    "CDD": {
        "error": 1.1489889921634623e-05, 
        "filter_outliers_dict": {
            "filter_outliers": true, 
            "iterations": 1, 
            "std_devs": 10
        }, 
        "fit": "average", 
        "value": 0.0001209371566575316
    }, 
    "H1": {
        "error": 0.003976116617718059, 
        "filter_outliers_dict": {
            "filter_outliers": true, 
            "iterations": 1, 
            "std_devs": 2
        }, 
        "fit": "average", 
        "value": 0.0033452409843933236
    }, 
    "H2": {
        "error": 0.006957738989661175, 
        "filter_outliers_dict": {
            "filter_outliers": true, 
            "iterations": 1, 
            "std_devs": 2
        }, 
        "fit": "average", 
        "value": -0.14422015275499883
    }, 
    "L1": {
        "error": 0.0018526095057081722, 
        "filter_outliers_dict": {
            "filter_outliers": true, 
            "iterations": 1, 
            "std_devs": 2
        }, 
        "fit": "average", 
        "value": -0.011575075137215562
    }, 
    "L2": {
        "error": 0.004627452836680823, 
        "filter_outliers_dict": {
            "filter_outliers": true, 
            "iterations": 1, 
            "std_devs": 2
        }, 
        "fit": "average", 
        "value": -0.010799878637662462
    }
}