{
    "Ar36": {
        "error": 0.00016084336859231878,
        "fit": "Bracketing Interpolate",
        "references": [
            {
                "exclude": "ok",
                "record_id": "bc-02-J-62",
                "uuid": "e6cb236d-cc37-4e00-9e33-1b321ef527e8"
            },
            {
                "exclude": "ok",
                "record_id": "bc-02-J-63",
                "uuid": "b6ddbe7c-2c02-41f0-81f2-a8476eb90d9e"
            },
            {
                "exclude": "ok",
                "record_id": "bc-02-J-64",
                "uuid": "1ce5b985-db77-4867-8a6d-042d8e1364e0"
            },
            {
                "exclude": "ok",
                "record_id": "bc-02-J-65",
                "uuid": "acb6f7db-78b2-46f5-80df-bb8c13ef9e31"
            },
            {
                "exclude": "ok",
                "record_id": "bc-02-J-66",
                "uuid": "868b81b9-3a87-4d03-9577-eaf792cbb63d"
            },
            {
                "exclude": "ok",
                "record_id": "bc-02-J-67",
                "uuid": "2d0e08b2-7d48-4e19-9091-b3dedde6153e"
            },
            {
                "exclude": "ok",
                "record_id": "bc-02-J-68",
                "uuid": "2ac4e545-5d9a-4018-a011-2c6e0677de38"
            }
        ],
        "reviewed": true,
        "value": 0.006395218695516644
    },
    "Ar37": {
        "error": 0.004595434408165801,
        "fit": "Bracketing Interpolate",
        "references": [
            {
                "exclude": "ok",
                "record_id": "bc-02-J-62",
                "uuid": "e6cb236d-cc37-4e00-9e33-1b321ef527e8"
            },
            {
                "exclude": "ok",
                "record_id": "bc-02-J-63",
                "uuid": "b6ddbe7c-2c02-41f0-81f2-a8476eb90d9e"
            },
            {
                "exclude": "ok",
                "record_id": "bc-02-J-64",
                "uuid": "1ce5b985-db77-4867-8a6d-042d8e1364e0"
            },
            {
                "exclude": "ok",
                "record_id": "bc-02-J-65",
                "uuid": "acb6f7db-78b2-46f5-80df-bb8c13ef9e31"
            },
            {
                "exclude": "ok",
                "record_id": "bc-02-J-66",
                "uuid": "868b81b9-3a87-4d03-9577-eaf792cbb63d"
            },
            {
                "exclude": "ok",
                "record_id": "bc-02-J-67",
                "uuid": "2d0e08b2-7d48-4e19-9091-b3dedde6153e"
            },
            {
                "exclude": "ok",
                "record_id": "bc-02-J-68",
                "uuid": "2ac4e545-5d9a-4018-a011-2c6e0677de38"
            }
        ],
        "reviewed": true,
        "value": 0.017347200552567027
    },
    "Ar38": {
        "error": 0.0020616349685545956,
        "fit": "Bracketing Interpolate",
        "references": [
            {
                "exclude": "ok",
                "record_id": "bc-02-J-62",
                "uuid": "e6cb236d-cc37-4e00-9e33-1b321ef527e8"
            },
            {
                "exclude": "ok",
                "record_id": "bc-02-J-63",
                "uuid": "b6ddbe7c-2c02-41f0-81f2-a8476eb90d9e"
            },
            {
                "exclude": "ok",
                "record_id": "bc-02-J-64",
                "uuid": "1ce5b985-db77-4867-8a6d-042d8e1364e0"
            },
            {
                "exclude": "ok",
                "record_id": "bc-02-J-65",
                "uuid": "acb6f7db-78b2-46f5-80df-bb8c13ef9e31"
            },
            {
                "exclude": "ok",
                "record_id": "bc-02-J-66",
                "uuid": "868b81b9-3a87-4d03-9577-eaf792cbb63d"
            },
            {
                "exclude": "ok",
                "record_id": "bc-02-J-67",
                "uuid": "2d0e08b2-7d48-4e19-9091-b3dedde6153e"
            },
            {
                "exclude": "ok",
                "record_id": "bc-02-J-68",
                "uuid": "2ac4e545-5d9a-4018-a011-2c6e0677de38"
            }
        ],
        "reviewed": true,
        "value": 0.015093246095283923
    },
    "Ar39": {
        "error": 0.007909999158511694,
        "fit": "Bracketing Interpolate",
        "references": [
            {
                "exclude": "ok",
                "record_id": "bc-02-J-62",
                "uuid": "e6cb236d-cc37-4e00-9e33-1b321ef527e8"
            },
            {
                "exclude": "ok",
                "record_id": "bc-02-J-63",
                "uuid": "b6ddbe7c-2c02-41f0-81f2-a8476eb90d9e"
            },
            {
                "exclude": "ok",
                "record_id": "bc-02-J-64",
                "uuid": "1ce5b985-db77-4867-8a6d-042d8e1364e0"
            },
            {
                "exclude": "ok",
                "record_id": "bc-02-J-65",
                "uuid": "acb6f7db-78b2-46f5-80df-bb8c13ef9e31"
            },
            {
                "exclude": "ok",
                "record_id": "bc-02-J-66",
                "uuid": "868b81b9-3a87-4d03-9577-eaf792cbb63d"
            },
            {
                "exclude": "ok",
                "record_id": "bc-02-J-67",
                "uuid": "2d0e08b2-7d48-4e19-9091-b3dedde6153e"
            },
            {
                "exclude": "ok",
                "record_id": "bc-02-J-68",
                "uuid": "2ac4e545-5d9a-4018-a011-2c6e0677de38"
            }
        ],
        "reviewed": true,
        "value": 0.051984922640874946
    },
    "Ar40": {
        "error": 0.00589754418450316,
        "fit": "Bracketing Interpolate",
        "references": [
            {
                "exclude": "ok",
                "record_id": "bc-02-J-62",
                "uuid": "e6cb236d-cc37-4e00-9e33-1b321ef527e8"
            },
            {
                "exclude": "ok",
                "record_id": "bc-02-J-63",
                "uuid": "b6ddbe7c-2c02-41f0-81f2-a8476eb90d9e"
            },
            {
                "exclude": "ok",
                "record_id": "bc-02-J-64",
                "uuid": "1ce5b985-db77-4867-8a6d-042d8e1364e0"
            },
            {
                "exclude": "ok",
                "record_id": "bc-02-J-65",
                "uuid": "acb6f7db-78b2-46f5-80df-bb8c13ef9e31"
            },
            {
                "exclude": "ok",
                "record_id": "bc-02-J-66",
                "uuid": "868b81b9-3a87-4d03-9577-eaf792cbb63d"
            },
            {
                "exclude": "ok",
                "record_id": "bc-02-J-67",
                "uuid": "2d0e08b2-7d48-4e19-9091-b3dedde6153e"
            },
            {
                "exclude": "ok",
                "record_id": "bc-02-J-68",
                "uuid": "2ac4e545-5d9a-4018-a011-2c6e0677de38"
            }
        ],
        "reviewed": true,
        "value": 0.31131643267258524
    },
    "Ar41": {
        "error": 0.004860969917806351,
        "fit": "previous",
        "references": [
            {
                "exclude": false,
                "record_id": "bc-02-J-62"
            }
        ],
        "value": 0.01564224940347017
    }
}