{
    "Ar36": {
        "error": 0.00045806702608532774, 
        "filter_outliers_dict": {
            "filter_outliers": true, 
            "iterations": 1, 
            "std_devs": 2
        }, 
        "fit": "Linear", 
        "value": 0.031188477639347605
    }, 
    "Ar37": {
        "error": 0.009692860476642803, 
        "filter_outliers_dict": {
            "filter_outliers": true, 
            "iterations": 1, 
            "std_devs": 2
        }, 
        "fit": "linear", 
        "value": 0.16238864487668314
    }, 
    "Ar38": {
        "error": 0.004749348779842772, 
        "filter_outliers_dict": {
            "filter_outliers": true, 
            "iterations": 1, 
            "std_devs": 2
        }, 
        "fit": "linear", 
        "value": 1.098355708488664
    }, 
    "Ar39": {
        "error": 0.019661284473342006, 
        "filter_outliers_dict": {
            "filter_outliers": true, 
            "iterations": 1, 
            "std_devs": 2
        }, 
        "fit": "Linear", 
        "value": 82.94243929804368
    }, 
    "Ar40": {
        "error": 0.05799981687404251, 
        "filter_outliers_dict": {
            "filter_outliers": true, 
            "iterations": 1, 
            "std_devs": 2
        }, 
        "fit": "Linear", 
        "value": 1029.4800606479366
    }, 
    "Ar41": {
        "error": 0.0047608392128142205, 
        "filter_outliers_dict": {
            "filter_outliers": true, 
            "iterations": 1, 
            "std_devs": 2
        }, 
        "fit": "Average", 
        "value": 0.12408430043119155
    }
}