{
    "Ar36": {
        "error": 0.0003164555011849784, 
        "filter_outliers_dict": {
            "filter_outliers": true, 
            "iterations": 1, 
            "std_devs": 2
        }, 
        "fit": "Parabolic", 
        "value": 0.030650683812748342
    }, 
    "Ar37": {
        "error": 0.004815712192465964, 
        "filter_outliers_dict": {
            "filter_outliers": true, 
            "iterations": 1, 
            "std_devs": 2
        }, 
        "fit": "linear", 
        "value": 0.1590354675357448
    }, 
    "Ar38": {
        "error": 0.002247229371990823, 
        "filter_outliers_dict": {
            "filter_outliers": true, 
            "iterations": 1, 
            "std_devs": 2
        }, 
        "fit": "linear", 
        "value": 1.0623103118576844
    }, 
    "Ar39": {
        "error": 0.015030131358919382, 
        "filter_outliers_dict": {
            "filter_outliers": true, 
            "iterations": 1, 
            "std_devs": 2
        }, 
        "fit": "Parabolic", 
        "value": 79.63430251227739
    }, 
    "Ar40": {
        "error": 0.04719485178533671, 
        "filter_outliers_dict": {
            "filter_outliers": true, 
            "iterations": 1, 
            "std_devs": 2
        }, 
        "fit": "Parabolic", 
        "value": 988.3661772857802
    }, 
    "Ar41": {
        "error": 0.005048004145999414, 
        "filter_outliers_dict": {
            "filter_outliers": true, 
            "iterations": 1, 
            "std_devs": 2
        }, 
        "fit": "linear", 
        "value": 0.11308799212921238
    }
}