{
    "Ar36": {
        "error": 0.0003645096918005372, 
        "filter_outliers_dict": {
            "filter_outliers": true, 
            "iterations": 1, 
            "std_devs": 2
        }, 
        "fit": "Linear", 
        "value": 0.029253813255680067
    }, 
    "Ar37": {
        "error": 0.009100024955639632, 
        "filter_outliers_dict": {
            "filter_outliers": true, 
            "iterations": 1, 
            "std_devs": 2
        }, 
        "fit": "linear", 
        "value": 0.15561228380974376
    }, 
    "Ar38": {
        "error": 0.004520028433361056, 
        "filter_outliers_dict": {
            "filter_outliers": true, 
            "iterations": 1, 
            "std_devs": 2
        }, 
        "fit": "linear", 
        "value": 1.0010648761533048
    }, 
    "Ar39": {
        "error": 0.017061470793041288, 
        "filter_outliers_dict": {
            "filter_outliers": true, 
            "iterations": 1, 
            "std_devs": 2
        }, 
        "fit": "Linear", 
        "value": 77.91096354583993
    }, 
    "Ar40": {
        "error": 0.06768782383769699, 
        "filter_outliers_dict": {
            "filter_outliers": true, 
            "iterations": 1, 
            "std_devs": 2
        }, 
        "fit": "Linear", 
        "value": 965.2990940379952
    }, 
    "Ar41": {
        "error": 0.00465165111313312, 
        "filter_outliers_dict": {
            "filter_outliers": true, 
            "iterations": 1, 
            "std_devs": 2
        }, 
        "fit": "Average", 
        "value": 0.12093467653366015
    }
}