{
    "Ar36": {
        "error": 0.0005251397645272449, 
        "filter_outliers_dict": {
            "filter_outliers": true, 
            "iterations": 1, 
            "std_devs": 2
        }, 
        "fit": "Linear", 
        "value": 0.04398540989611026
    }, 
    "Ar37": {
        "error": 0.010203336639507812, 
        "filter_outliers_dict": {
            "filter_outliers": true, 
            "iterations": 1, 
            "std_devs": 2
        }, 
        "fit": "linear", 
        "value": 0.16318099774326378
    }, 
    "Ar38": {
        "error": 0.004386205533386053, 
        "filter_outliers_dict": {
            "filter_outliers": true, 
            "iterations": 1, 
            "std_devs": 2
        }, 
        "fit": "linear", 
        "value": 0.9888717267699009
    }, 
    "Ar39": {
        "error": 0.019655680413989445, 
        "filter_outliers_dict": {
            "filter_outliers": true, 
            "iterations": 1, 
            "std_devs": 2
        }, 
        "fit": "Linear", 
        "value": 73.11525994251151
    }, 
    "Ar40": {
        "error": 0.045506286734840515, 
        "filter_outliers_dict": {
            "filter_outliers": true, 
            "iterations": 1, 
            "std_devs": 2
        }, 
        "fit": "Linear", 
        "value": 908.3485406203491
    }, 
    "Ar41": {
        "error": 0.004623233850166427, 
        "filter_outliers_dict": {
            "filter_outliers": true, 
            "iterations": 1, 
            "std_devs": 2
        }, 
        "fit": "Average", 
        "value": 0.23245409911223108
    }
}