{
    "Ar36": {
        "error": 0.0003550769985213684, 
        "filter_outliers": true, 
        "filter_outliers_dict": {
            "filter_outliers": true, 
            "iterations": 1, 
            "std_devs": 2
        }, 
        "fit": "Parabolic", 
        "fn": 385, 
        "include_baseline_error": false, 
        "iterations": 1, 
        "n": 400, 
        "std_devs": 2, 
        "value": 0.0349811704803554
    }, 
    "Ar37": {
        "error": 0.005019796458352714, 
        "filter_outliers": true, 
        "filter_outliers_dict": {
            "filter_outliers": true, 
            "iterations": 1, 
            "std_devs": 2
        }, 
        "fit": "Linear", 
        "fn": 380, 
        "include_baseline_error": false, 
        "iterations": 1, 
        "n": 400, 
        "std_devs": 2, 
        "value": 0.015190870243967345
    }, 
    "Ar38": {
        "error": 0.00223966023374635, 
        "filter_outliers": true, 
        "filter_outliers_dict": {
            "filter_outliers": true, 
            "iterations": 1, 
            "std_devs": 2
        }, 
        "fit": "Linear", 
        "fn": 385, 
        "include_baseline_error": false, 
        "iterations": 1, 
        "n": 400, 
        "std_devs": 2, 
        "value": 0.8900055006910701
    }, 
    "Ar39": {
        "error": 0.014516734497031135, 
        "filter_outliers": true, 
        "filter_outliers_dict": {
            "filter_outliers": true, 
            "iterations": 1, 
            "std_devs": 2
        }, 
        "fit": "Parabolic", 
        "fn": 382, 
        "include_baseline_error": false, 
        "iterations": 1, 
        "n": 400, 
        "std_devs": 2, 
        "value": 69.23027786299897
    }, 
    "Ar40": {
        "error": 0.039329720628701006, 
        "filter_outliers": true, 
        "filter_outliers_dict": {
            "filter_outliers": true, 
            "iterations": 1, 
            "std_devs": 2
        }, 
        "fit": "Parabolic", 
        "fn": 379, 
        "include_baseline_error": false, 
        "iterations": 1, 
        "n": 400, 
        "std_devs": 2, 
        "value": 860.2942693598259
    }, 
    "Ar41": {
        "error": 0.003019209847855576, 
        "filter_outliers": true, 
        "filter_outliers_dict": {
            "filter_outliers": true, 
            "iterations": 1, 
            "std_devs": 2
        }, 
        "fit": "Average", 
        "fn": 382, 
        "include_baseline_error": false, 
        "iterations": 1, 
        "n": 400, 
        "std_devs": 2, 
        "value": -0.028250820717293738
    }, 
    "reviewed": true
}