{
    "Ar36": {
        "error": 0.00039139646250039065, 
        "filter_outliers": true, 
        "filter_outliers_dict": {
            "filter_outliers": true, 
            "iterations": 1, 
            "std_devs": 2
        }, 
        "fit": "Parabolic", 
        "fn": 385, 
        "include_baseline_error": false, 
        "iterations": 1, 
        "n": 400, 
        "std_devs": 2, 
        "value": 0.03502964557711736
    }, 
    "Ar37": {
        "error": 0.004936466004014979, 
        "filter_outliers": true, 
        "filter_outliers_dict": {
            "filter_outliers": true, 
            "iterations": 1, 
            "std_devs": 2
        }, 
        "fit": "Linear", 
        "fn": 383, 
        "include_baseline_error": false, 
        "iterations": 1, 
        "n": 400, 
        "std_devs": 2, 
        "value": 0.01643171422389882
    }, 
    "Ar38": {
        "error": 0.0022280361091656722, 
        "filter_outliers": true, 
        "filter_outliers_dict": {
            "filter_outliers": true, 
            "iterations": 1, 
            "std_devs": 2
        }, 
        "fit": "Linear", 
        "fn": 383, 
        "include_baseline_error": false, 
        "iterations": 1, 
        "n": 400, 
        "std_devs": 2, 
        "value": 0.9002349572226883
    }, 
    "Ar39": {
        "error": 0.013815549210482324, 
        "filter_outliers": true, 
        "filter_outliers_dict": {
            "filter_outliers": true, 
            "iterations": 1, 
            "std_devs": 2
        }, 
        "fit": "Parabolic", 
        "fn": 383, 
        "include_baseline_error": false, 
        "iterations": 1, 
        "n": 400, 
        "std_devs": 2, 
        "value": 69.30926441242164
    }, 
    "Ar40": {
        "error": 0.0396584655836216, 
        "filter_outliers": true, 
        "filter_outliers_dict": {
            "filter_outliers": true, 
            "iterations": 1, 
            "std_devs": 2
        }, 
        "fit": "Parabolic", 
        "fn": 386, 
        "include_baseline_error": false, 
        "iterations": 1, 
        "n": 400, 
        "std_devs": 2, 
        "value": 860.9882878929179
    }, 
    "Ar41": {
        "error": 0.002985996595118805, 
        "filter_outliers": true, 
        "filter_outliers_dict": {
            "filter_outliers": true, 
            "iterations": 1, 
            "std_devs": 2
        }, 
        "fit": "Average", 
        "fn": 380, 
        "include_baseline_error": false, 
        "iterations": 1, 
        "n": 400, 
        "std_devs": 2, 
        "value": -0.020504893816474867
    }, 
    "reviewed": true
}