{
    "AX": {
        "error": 0.004663661423329796, 
        "filter_outliers_dict": {
            "filter_outliers": true, 
            "iterations": 1, 
            "std_devs": 2
        }, 
        "fit": "average", 
        "value": -0.038108662241329694
    }, 
    "CDD": {
        "error": 3.7534007247095324e-06, 
        "filter_outliers_dict": {
            "filter_outliers": true, 
            "iterations": 1, 
            "std_devs": 10
        }, 
        "fit": "average", 
        "value": 1.2345312040055583e-05
    }, 
    "H1": {
        "error": 0.003552946651578319, 
        "filter_outliers_dict": {
            "filter_outliers": true, 
            "iterations": 1, 
            "std_devs": 2
        }, 
        "fit": "average", 
        "value": -0.03818826611845616
    }, 
    "H2": {
        "error": 0.005426862924127385, 
        "filter_outliers_dict": {
            "filter_outliers": true, 
            "iterations": 1, 
            "std_devs": 2
        }, 
        "fit": "average", 
        "value": -0.13963304137021051
    }, 
    "L1": {
        "error": 0.0018140362933844795, 
        "filter_outliers_dict": {
            "filter_outliers": true, 
            "iterations": 1, 
            "std_devs": 2
        }, 
        "fit": "average", 
        "value": -0.017870941505450096
    }, 
    "L2": {
        "error": 0.004122512629291917, 
        "filter_outliers_dict": {
            "filter_outliers": true, 
            "iterations": 1, 
            "std_devs": 2
        }, 
        "fit": "average", 
        "value": -0.020471798977657704
    }
}